altxria/iris/__init__.py
altxria/iris/cache.py
altxria/iris/directives.py
altxria/iris/engine.py
altxria/iris/exceptions.py
altxria/iris/parser.py
iris_templates-0.1.2.dist-info/LICENSE
iris_templates-0.1.2.dist-info/METADATA
iris_templates-0.1.2.dist-info/WHEEL
iris_templates-0.1.2.dist-info/entry_points.txt
iris_templates-0.1.2.dist-info/top_level.txt
iris_templates-0.1.2.dist-info/RECORD
