Metadata-Version: 2.1
Name: iris-templates
Version: 0.1.2
Summary: A powerful template rendering engine with support for directives, includes, and dynamic context evaluation.
Author-email: "Altxria Inc." <company@altxria.com>
License: Attribution-NoDerivatives 4.0 International
Project-URL: Bug Tracker, https://github.com/yourusername/iris/issues
Project-URL: Documentation, https://github.com/yourusername/iris/wiki
Project-URL: Source Code, https://github.com/yourusername/iris
Keywords: template engine,rendering,includes,directives
Classifier: Development Status :: 3 - Alpha
Classifier: Intended Audience :: Developers
Classifier: License :: Other/Proprietary License
Classifier: Programming Language :: Python :: 3
Classifier: Programming Language :: Python :: 3.7
Classifier: Programming Language :: Python :: 3.8
Classifier: Programming Language :: Python :: 3.9
Classifier: Programming Language :: Python :: 3.10
Classifier: Programming Language :: Python :: 3.11
Classifier: Operating System :: OS Independent
Requires-Python: >=3.7
License-File: LICENSE
Provides-Extra: dev
Requires-Dist: pytest>=7.0; extra == "dev"
Requires-Dist: black>=23.0; extra == "dev"
Requires-Dist: flake8>=6.0; extra == "dev"
